awscfncli/__init__.py
awscfncli/__main__.py
awscfncli/cli.py
awscfncli/config.py
awscfncli/commands/__init__.py
awscfncli/commands/utils.py
awscfncli/commands/changeset/__init__.py
awscfncli/commands/changeset/create.py
awscfncli/commands/changeset/describe.py
awscfncli/commands/changeset/execute.py
awscfncli/commands/changeset/list_.py
awscfncli/commands/stack/__init__.py
awscfncli/commands/stack/delete.py
awscfncli/commands/stack/deploy.py
awscfncli/commands/stack/describe.py
awscfncli/commands/stack/events.py
awscfncli/commands/stack/set_termination_protection.py
awscfncli/commands/stack/tail.py
awscfncli/commands/stack/update.py
awscfncli/commands/template/__init__.py
awscfncli/commands/template/costs.py
awscfncli/commands/template/package.py
awscfncli/commands/template/reflect.py
awscfncli/commands/template/validate.py
awscfncli-0.5.2.dist-info/DESCRIPTION.rst
awscfncli-0.5.2.dist-info/METADATA
awscfncli-0.5.2.dist-info/RECORD
awscfncli-0.5.2.dist-info/WHEEL
awscfncli-0.5.2.dist-info/entry_points.txt
awscfncli-0.5.2.dist-info/metadata.json
awscfncli-0.5.2.dist-info/top_level.txt
tests/commands/__init__.py
tests/commands/boto_mock.py
tests/commands/test_changeset.py
tests/commands/test_stack.py
tests/commands/test_template.py
